alegbra.py
alegbra-1.0.dist-info/METADATA
alegbra-1.0.dist-info/WHEEL
alegbra-1.0.dist-info/top_level.txt
alegbra-1.0.dist-info/RECORD
