Metadata-Version: 2.1
Name: alegbra
Version: 1.0
Summary: A package that can perform alegbric functions . 
Home-page: https://github.com/Harinisaras/alegbra.git
Author: Harini.T,Venkateswar.S 
Author-email: harinisarasv@gmail.com
License: UNKNOWN
Platform: UNKNOWN
Classifier: Programming Language :: Python :: 3.5
Classifier: Programming Language :: Python :: 3.6
Classifier: Programming Language :: Python :: 3.7
Classifier: Programming Language :: Python :: 3.8
Classifier: Operating System :: OS Independent
